ruamel.db.base-0.2.3-py3.10-nspkg.pth
ruamel/db/base/__init__.py
ruamel/db/base/diffdict.py
ruamel/db/base/key_nr.py
ruamel/db/base/log.py
ruamel/db/base/microsecstamp.py
ruamel.db.base-0.2.3.dist-info/METADATA
ruamel.db.base-0.2.3.dist-info/WHEEL
ruamel.db.base-0.2.3.dist-info/namespace_packages.txt
ruamel.db.base-0.2.3.dist-info/top_level.txt
ruamel.db.base-0.2.3.dist-info/RECORD
